MANIFEST.in
README.md
setup.cfg
setup.py
valleydata/DataGenerator.py
valleydata/TextAnalyzer.py
valleydata/__init__.py
valleydata/exceptions.py
valleydata/valleydata.py
valleydata.egg-info/PKG-INFO
valleydata.egg-info/SOURCES.txt
valleydata.egg-info/dependency_links.txt
valleydata.egg-info/top_level.txt