Metadata-Version: 1.1
Name: valleydata
Version: 0.0.9
Summary: ValleyData
Home-page: https://github.com/valleyworks/valleydata
Author: Nahuel Chaves
Author-email: nahuel.chaves@valleyworks.us
License: MIT
Keywords: valleydata valleyworks
Platform: UNKNOWN
Classifier: Development Status :: 3 - Alpha
Classifier: Intended Audience :: Developers
Classifier: License :: OSI Approved :: MIT License
Classifier: Programming Language :: Python :: 3
Classifier: Programming Language :: Python :: 3.3
Classifier: Programming Language :: Python :: 3.4
Classifier: Programming Language :: Python :: 3.5
